MANIFEST.in
README
mysql-autodoc
setup.py
mysql_autodoc/__init__.py
mysql_autodoc/db.tmpl
mysql_autodoc.egg-info/PKG-INFO
mysql_autodoc.egg-info/SOURCES.txt
mysql_autodoc.egg-info/dependency_links.txt
mysql_autodoc.egg-info/entry_points.txt
mysql_autodoc.egg-info/requires.txt
mysql_autodoc.egg-info/top_level.txt