Metadata-Version: 1.0
Name: mysql-autodoc
Version: 0.2
Summary: Generate HTML documentation from a mysql database
Home-page: http://www.pegueroles.com/
Author: Ferran Pegueroles Forcadell
Author-email: ferran@pegueroles.com
License: GPL
Download-URL: https://bitbucket.org/ferranp/mysql-autodoc/downloads
Platform: linux
Platform: windows
Classifier: Development Status :: 5 - Production/Stable
Classifier: Environment :: Console
Classifier: Intended Audience :: Developers
Classifier: Intended Audience :: Information Technology
Classifier: Intended Audience :: System Administrators
Classifier: License :: OSI Approved :: GNU General Public License (GPL)
Classifier: Programming Language :: Python
Classifier: Topic :: Database
Classifier: Topic :: Utilities
Classifier: Topic :: Documentation
